Melodie/__init__.py
Melodie/__main__.py
Melodie/calibrator.py
Melodie/data_collector.py
Melodie/data_loader.py
Melodie/element.py
Melodie/global_configs.py
Melodie/model.py
Melodie/network.py
Melodie/scenario_manager.py
Melodie/simulator.py
Melodie/table_generator.py
Melodie/trainer.py
Melodie/version.txt
Melodie/algorithms/__init__.py
Melodie/algorithms/algorithm_param.py
Melodie/algorithms/ga.py
Melodie/utils/__init__.py
Melodie/utils/checker.py
Melodie/utils/profiler.py
Melodie/utils/system_info.py
Melodie/utils/unsafe.py
Melodie/visualizer/__init__.py
Melodie/visualizer/actions.py
Melodie/visualizer/vis_agent_series.py
Melodie/visualizer/vis_charts.py
Melodie/visualizer/visualizer.py
Melodie/visualizer/visualizer_server.py
MelodieInfra/__init__.py
MelodieInfra/action/__init__.py
MelodieInfra/action/action.py
MelodieInfra/action/process.py
MelodieInfra/boost/__init__.py
MelodieInfra/boost/numba_numpy_run.py
MelodieInfra/boost/numba_utils.py
MelodieInfra/compat/__init__.py
MelodieInfra/compat/compat.py
MelodieInfra/config/__init__.py
MelodieInfra/config/config.py
MelodieInfra/config/global_configs.py
MelodieInfra/core/__init__.py
MelodieInfra/core/agent.py
MelodieInfra/core/agent_list.py
MelodieInfra/core/api.py
MelodieInfra/core/environment.py
MelodieInfra/core/grid.py
MelodieInfra/core/scenario.py
MelodieInfra/core/types.py
MelodieInfra/db/__init__.py
MelodieInfra/db/base.py
MelodieInfra/db/db.py
MelodieInfra/db/db_configs.py
MelodieInfra/exceptions/__init__.py
MelodieInfra/exceptions/exceptions.py
MelodieInfra/exceptions/pretty_warnings.py
MelodieInfra/exceptions/troubleshooting.py
MelodieInfra/jsonobject/__init__.py
MelodieInfra/jsonobject/api.py
MelodieInfra/jsonobject/base.py
MelodieInfra/jsonobject/base_properties.py
MelodieInfra/jsonobject/containers.py
MelodieInfra/jsonobject/exceptions.py
MelodieInfra/jsonobject/properties.py
MelodieInfra/jsonobject/utils.py
MelodieInfra/lowcode/__init__.py
MelodieInfra/lowcode/params.py
Melodie-1.0.1.dist-info/LICENSE.txt
Melodie-1.0.1.dist-info/METADATA
Melodie-1.0.1.dist-info/WHEEL
Melodie-1.0.1.dist-info/entry_points.txt
Melodie-1.0.1.dist-info/top_level.txt
Melodie-1.0.1.dist-info/RECORD
