Metadata-Version: 2.1
Name: Melodie
Version: 1.0.1
Summary: A general framework that can be used to establish agent-based models for specific uses.
Home-page: https://github.com/ABM4ALL/Melodie
Author: Songmin Yu, Zhanyi Hou
Author-email: abm4all@outlook.com
License: MIT
Project-URL: Documentation, http://docs.abm4all.com
Classifier: Development Status :: 4 - Beta
Classifier: Intended Audience :: Science/Research
Classifier: License :: OSI Approved :: MIT License
Classifier: Natural Language :: English
Classifier: Operating System :: Unix
Classifier: Operating System :: Microsoft :: Windows
Classifier: Programming Language :: Python :: 3.8
Classifier: Programming Language :: Python :: 3.9
Classifier: Programming Language :: Python :: 3.10
Classifier: Programming Language :: Python :: 3.11
Classifier: Programming Language :: Python :: 3.12
Classifier: Topic :: Scientific/Engineering :: Artificial Intelligence
Requires-Python: >=3.8
License-File: LICENSE.txt
Requires-Dist: numpy
Requires-Dist: matplotlib
Requires-Dist: scipy
Requires-Dist: chardet
Requires-Dist: pandas
Requires-Dist: seaborn
Requires-Dist: networkx
Requires-Dist: openpyxl
Requires-Dist: sqlalchemy >=2.0
Requires-Dist: sqlalchemy-utils
Requires-Dist: astunparse
Requires-Dist: pprintast
Requires-Dist: cloudpickle
Requires-Dist: scikit-opt ~=0.6
Requires-Dist: rpyc
Requires-Dist: flask
Requires-Dist: flask-cors
Requires-Dist: flask-sock
